{
    "hindu": [
        {
            "text": "Whose stick, his buffalo.",
            "description": "",
            "category": "hindu"
        },
        {
            "text": "Eating while seated makes one of large size; eating while standing makes one strong.",
            "description": "",
            "category": "hindu"
        },
        {
            "text": "Can the monkey know the taste of ginger?",
            "description": "",
            "category": "hindu"
        },
        {
            "text": "When an elephant is in trouble even a frog will kick him. ",
            "description": "",
            "category": "hindu"
        },
        {
            "text": "Eating while seated makes one of large size; eating while standing makes one strong.",
            "description": "",
            "category": "hindu"
        },
        {
            "text": "When an elephant is in trouble even a frog will kick him.",
            "description": "",
            "category": "hindu"
        },
        {
            "text": "Of what use is the veil if you are going to dance.",
            "description": "",
            "category": "hindu"
        },
        {
            "text": "Wash your hands in the flowing Ganges.",
            "description": "",
            "category": "hindu"
        },
        {
            "text": "Of what use is the veil if you are going to dance.",
            "description": "",
            "category": "hindu"
        },
        {
            "text": "When an elephant is in trouble even a frog will kick him.",
            "description": "",
            "category": "hindu"
        },
        {
            "text": "Give your ears to words but do not give your words to ears.",
            "description": "",
            "category": "hindustani"
        },
        {
            "text": "True happiness consists in making others happy.",
            "description": "",
            "category": "hindu"
        },
        {
            "text": "Real happiness consists in making others happy.",
            "description": "",
            "category": "hindu"
        },
        {
            "text": "Help thy brother’s boat across, and lo! thine own has reached the shore.",
            "description": "",
            "category": "hindu"
        },
        {
            "text": "No sooner have you spoken than what you have said becomes the property of another.",
            "description": "",
            "category": "hindustani"
        },
        {
            "text": "Wash your hands in the flowing Ganges.",
            "description": "",
            "category": "hindu"
        },
        {
            "text": "The adult looks to deeds, the child to love.",
            "description": "",
            "category": "hindustani"
        },
        {
            "text": "Many dogs kill a hare, no matter how many turns it makes.",
            "description": "",
            "category": "hindu"
        },
        {
            "text": "When a camel is at the foot of a mountain then judge of his height.",
            "description": "",
            "category": "hindu"
        },
        {
            "text": "Waste not want not.",
            "description": "",
            "category": "hindu"
        },
        {
            "text": "Waste makes want.",
            "description": "",
            "category": "hindu"
        },
        {
            "text": "Wash your hands in the flowing Ganges.",
            "description": "",
            "category": "hindu"
        },
        {
            "text": "True happiness consists in making others happy.",
            "description": "",
            "category": "hindu"
        },
        {
            "text": "To give quickly is a great virtue.",
            "description": "",
            "category": "hindu"
        },
        {
            "text": "Those who give have all things; those who withhold have nothing.",
            "description": "",
            "category": "hindu"
        },
        {
            "text": "These three take crooked ways: carts, boats, and musicians.",
            "description": "",
            "category": "hindu"
        },
        {
            "text": "Sleep after selling horses and elephants.",
            "description": "",
            "category": "hindu"
        },
        {
            "text": "Saints fly only in the eyes of their disciples.",
            "description": "",
            "category": "hindu"
        },
        {
            "text": "Of what use is the veil if you are going to dance.",
            "description": "",
            "category": "hindu"
        },
        {
            "text": "Never strike your wife, even with a flower.",
            "description": "",
            "category": "hindu"
        },
        {
            "text": "Many dogs kill a hare, no matter how many turns it makes.",
            "description": "",
            "category": "hindu"
        },
        {
            "text": "Like the body that is made up of different limbs and organs, all mortal creatures exist depending upon one another.",
            "description": "",
            "category": "hindu"
        },
        {
            "text": "Kill a cow to donate shoes.",
            "description": "",
            "category": "hindu"
        },
        {
            "text": "It is better to walk than to run; it is better to stand than to walk; it is better to sit than to stand; it is better to lie than to sit.",
            "description": "",
            "category": "hindu"
        },
        {
            "text": "Help your brother’s boat across, and your own will reach the shore.",
            "description": "",
            "category": "hindu"
        },
        {
            "text": "He who does kind deeds becomes rich.",
            "description": "",
            "category": "hindu"
        },
        {
            "text": "Eating while seated makes one of large size; eating while standing makes one strong.",
            "description": "",
            "category": "hindu"
        },
        {
            "text": "Dig your well before you’re thirsty.",
            "description": "",
            "category": "hindu"
        },
        {
            "text": "Dig a well every day to drink water every day.",
            "description": "",
            "category": "hindu"
        },
        {
            "text": "Can’t tell his ass from a hole in the ground.",
            "description": "",
            "category": "hindu"
        },
        {
            "text": "Can the monkey know the taste of ginger?",
            "description": "",
            "category": "hindu"
        },
        {
            "text": "Anger has no eyes.",
            "description": "",
            "category": "hindu"
        },
        {
            "text": "Among the blind, the squint rules.",
            "description": "",
            "category": "hindu"
        },
        {
            "text": "A man in this world without learning is as a beast of the field.",
            "description": "",
            "category": "hindu"
        },
        {
            "text": "A man becomes like those whose society he loves.",
            "description": "",
            "category": "hindu"
        }
    ]
}
