{
    "indonesian": [
        {
            "text": "With willingness, there is a possibility.",
            "description": "",
            "category": "indonesian"
        },
        {
            "text": "Every hill has its leopard.",
            "description": "",
            "category": "bahaya"
        },
        {
            "text": "Eyes watch but cannot take.",
            "description": "",
            "category": "bahaya"
        },
        {
            "text": "One piece of green wood is enough to stop the others from burning.",
            "description": "",
            "category": "bahaya"
        },
        {
            "text": "The mouth does not forget what it tasted only one time.",
            "description": "",
            "category": "bahaya"
        },
        {
            "text": "We rest our legs, but never our mouths.",
            "description": "",
            "category": "bahaya"
        },
        {
            "text": "Goodness shouts. Evil whispers.",
            "description": "",
            "category": "balinese"
        },
        {
            "text": "God does not ask to withstand more than is possible.",
            "description": "",
            "category": "amara"
        },
        {
            "text": "If you are happy you can always learn to dance.",
            "description": "",
            "category": "balinese"
        },
        {
            "text": "Skill is only a rumour, until it reaches the muscle.",
            "description": "",
            "category": "balinese"
        },
        {
            "text": "We have no art. We do everything as well as we can.",
            "description": "",
            "category": "balinese"
        },
        {
            "text": "We work on the surface, the depths are a mystery.",
            "description": "",
            "category": "bahaya"
        },
        {
            "text": "A mother is like a kernel, crushed by problems but strong enough to overcome them.",
            "description": "",
            "category": "balari"
        },
        {
            "text": "There is no hiding place on the water surface.",
            "description": "",
            "category": "balari"
        },
        {
            "text": "Who guards two termite hills, returns empty handed.",
            "description": "",
            "category": "bahaya"
        },
        {
            "text": "You only understand the joys of parenthood when you have your first child, you only understand the mystery of death when in mourning.",
            "description": "",
            "category": "bahaya"
        },
        {
            "text": "Where the heart is willing it will find a thousand ways, but where it is unwilling it will find a thousand excuses.",
            "description": "",
            "category": "dayak"
        },
        {
            "text": "Don't stay on the dew until the sun reaches its highest.",
            "description": "",
            "category": "indonesian"
        },
        {
            "text": "Each is dependent on the other for their mutual survival.",
            "description": "",
            "category": "indonesian"
        },
        {
            "text": "Even things that are far apart can meet as one.",
            "description": "",
            "category": "indonesian"
        },
        {
            "text": "Every action has its consequences.",
            "description": "",
            "category": "indonesian"
        },
        {
            "text": "Expecting something bigger, and we let go what we already have.",
            "description": "",
            "category": "indonesian"
        },
        {
            "text": "Expense is bigger than income.",
            "description": "",
            "category": "indonesian"
        },
        {
            "text": "Fighting a losing battle.",
            "description": "",
            "category": "indonesian"
        },
        {
            "text": "If an eel is with fish, he shows his tail; if he is with snakes, he shows his head.",
            "description": "",
            "category": "indonesian"
        },
        {
            "text": "If we do a lot of practice we can do a good job.",
            "description": "",
            "category": "indonesian"
        },
        {
            "text": "Wherever we live, we must observe the local custom.",
            "description": "",
            "category": "indonesian"
        },
        {
            "text": "Describe, usually with regret, something that has already happenned and is irreversible.",
            "description": "",
            "category": "indonesian"
        },
        {
            "text": "Different background means different thinking.",
            "description": "",
            "category": "indonesian"
        },
        {
            "text": "Different culture means different custom.",
            "description": "",
            "category": "indonesian"
        },
        {
            "text": "Different fields, different grasshoppers; different seas, different fish.",
            "description": "",
            "category": "indonesian"
        },
        {
            "text": "Different men have different opinions -- some prefer apples, some onions.",
            "description": "",
            "category": "indonesian"
        },
        {
            "text": "Different people have different personality.",
            "description": "",
            "category": "indonesian"
        },
        {
            "text": "Diligence is the beginning of brilliance.",
            "description": "",
            "category": "indonesian"
        },
        {
            "text": "Do multiple tasks at one go.",
            "description": "",
            "category": "indonesian"
        },
        {
            "text": "Do two things at one go.",
            "description": "",
            "category": "indonesian"
        },
        {
            "text": "Does not mix well together.",
            "description": "",
            "category": "indonesian"
        },
        {
            "text": "Together in good and bad times.",
            "description": "",
            "category": "indonesian"
        },
        {
            "text": "Two things that never get along.",
            "description": "",
            "category": "indonesian"
        },
        {
            "text": "Useless protest, critic, or sarcasm.",
            "description": "",
            "category": "indonesian"
        },
        {
            "text": "We are never satisfied with our posessions.",
            "description": "",
            "category": "indonesian"
        },
        {
            "text": "We have to fight for our freedom as long as it takes, and we shall not mind the death following our struggle for independence.",
            "description": "",
            "category": "indonesian"
        },
        {
            "text": "We only call our friends if we need help, and we don't help our friends in need.",
            "description": "",
            "category": "indonesian"
        },
        {
            "text": "When a durian tree is already ripe and sweet, many of the durians will fall to the ground.",
            "description": "",
            "category": "indonesian"
        },
        {
            "text": "When prominent persons fights, commoners would suffer.",
            "description": "",
            "category": "indonesian"
        },
        {
            "text": "When you begin to understand the situation, you know you must have been ill-informed.",
            "description": "",
            "category": "indonesian"
        },
        {
            "text": "Where's no top dogs, underdogs will be seen as one.",
            "description": "",
            "category": "indonesian"
        },
        {
            "text": "A change of event such as the death of a leader, will lead to other changes.",
            "description": "",
            "category": "indonesian"
        },
        {
            "text": "A different way of thingking in every person.",
            "description": "",
            "category": "indonesian"
        },
        {
            "text": "A dispute can only be resolved by discussing the problem openly and coolly.",
            "description": "",
            "category": "indonesian"
        },
        {
            "text": "A fire will sear and the sun burn yet more, but neither can match the ardor of a man's heart.",
            "description": "",
            "category": "indonesian"
        },
        {
            "text": "A good deed that is repaid by a bad deed.",
            "description": "",
            "category": "indonesian"
        },
        {
            "text": "A junior will always do what the senior does.",
            "description": "",
            "category": "indonesian"
        },
        {
            "text": "A long dispute has been forgoten by love, or sometimes a long time of goodness has been forgotten by one badness.",
            "description": "",
            "category": "indonesian"
        },
        {
            "text": "A man finds what he takes to be small; it will only be big again when he loses it.",
            "description": "",
            "category": "indonesian"
        },
        {
            "text": "A moth will eat the finest linen.",
            "description": "",
            "category": "indonesian"
        },
        {
            "text": "A mother's love is neverending.",
            "description": "",
            "category": "indonesian"
        },
        {
            "text": "If you are desperate, you must not be choosy.",
            "description": "",
            "category": "indonesian"
        },
        {
            "text": "If you enter a goat stable, bleat; if you enter a water buffalo stable, bellow.",
            "description": "",
            "category": "indonesian"
        },
        {
            "text": "If you go into a goat stable, bleat; if you go into a water buffalo stable, bellow.",
            "description": "",
            "category": "indonesian"
        },
        {
            "text": "In a no-win situation where all the possible solutions present has terrible consequences.",
            "description": "",
            "category": "indonesian"
        },
        {
            "text": "In a very critical situation as the egg will soon tip-over and fall.",
            "description": "",
            "category": "indonesian"
        },
        {
            "text": "Like the seaweed that clings to each other after each passing boat separates them, so too a family will come together with the passing of each crisis.",
            "description": "",
            "category": "indonesian"
        },
        {
            "text": "Live a good and useful life.",
            "description": "",
            "category": "indonesian"
        },
        {
            "text": "Never take for granted a quiet person, for he may have qualities that belie his quiet nature.",
            "description": "",
            "category": "indonesian"
        },
        {
            "text": "Never underestimate a quiet person, for he may have qualities that belie his quiet nature.",
            "description": "",
            "category": "indonesian"
        },
        {
            "text": "No experience, narrow minded.",
            "description": "",
            "category": "indonesian"
        },
        {
            "text": "The firm tree does not fear the storm.",
            "description": "",
            "category": "indonesian"
        },
        {
            "text": "The laughter of someone pining for his beloved is like that of someone who is always crying.",
            "description": "",
            "category": "indonesian"
        },
        {
            "text": "The name of Love's fiancis Divorce.",
            "description": "",
            "category": "indonesian"
        },
        {
            "text": "The opposite of It's A Small World.",
            "description": "",
            "category": "indonesian"
        },
        {
            "text": "The sea becomes the shore, the shore becomes the sea.",
            "description": "",
            "category": "indonesian"
        },
        {
            "text": "The shadow should be the same length as the body.",
            "description": "",
            "category": "indonesian"
        },
        {
            "text": "The shallower the brook, the more it babbles.",
            "description": "",
            "category": "indonesian"
        },
        {
            "text": "There are hidden purposes behind an act.",
            "description": "",
            "category": "indonesian"
        },
        {
            "text": "There are not many who would announce their faults with a gong.",
            "description": "",
            "category": "indonesian"
        },
        {
            "text": "There is always someone who loves you, and someone who hates you.",
            "description": "",
            "category": "indonesian"
        },
        {
            "text": "one ill behaviour may cause others to forget the kindness we've done.",
            "description": "",
            "category": "indonesian"
        },
        {
            "text": "People seek out big shots as flies seek out the elephant's tail.",
            "description": "",
            "category": "indonesian"
        },
        {
            "text": "People tend to be attracted to what most benefits them.",
            "description": "",
            "category": "indonesian"
        },
        {
            "text": "People with much ado usually don't know shallow.",
            "description": "",
            "category": "indonesian"
        },
        {
            "text": "Rippling water shows lack of depth.",
            "description": "",
            "category": "indonesian"
        },
        {
            "text": "Someone who doesn't want to be responsible for his doing.",
            "description": "",
            "category": "indonesian"
        },
        {
            "text": "Someone who expect to become someone that beyond him.",
            "description": "",
            "category": "indonesian"
        },
        {
            "text": "Someone who wish something impossible.",
            "description": "",
            "category": "indonesian"
        },
        {
            "text": "Someone will be remembered by his accolades.",
            "description": "",
            "category": "indonesian"
        },
        {
            "text": "Taking advantage of a murky/confusing situation.",
            "description": "",
            "category": "indonesian"
        },
        {
            "text": "There is no point of nurturing an anger inside us. Just let it go.",
            "description": "",
            "category": "indonesian"
        },
        {
            "text": "There will be a replacement for everything.",
            "description": "",
            "category": "indonesian"
        },
        {
            "text": "There's a cause of everything.",
            "description": "",
            "category": "indonesian"
        },
        {
            "text": "They are flies that are born of a wasp.",
            "description": "",
            "category": "indonesian"
        },
        {
            "text": "Think everything carefully before committing yourself because there is no point for regretting it later.",
            "description": "",
            "category": "indonesian"
        },
        {
            "text": "This proverb is often used to illustrate a person who does not have enough resources to accomplish his goal.",
            "description": "",
            "category": "indonesian"
        },
        {
            "text": "To be a smart man you need to be humble.",
            "description": "",
            "category": "indonesian"
        },
        {
            "text": "To describe a person who has just gotten out from a precarious situation just to get into another precarious situation.",
            "description": "",
            "category": "indonesian"
        },
        {
            "text": "To describe a unity of a society.",
            "description": "",
            "category": "indonesian"
        },
        {
            "text": "To get something one silently wishes for.",
            "description": "",
            "category": "indonesian"
        },
        {
            "text": "No matter how smart a person is, eventually he will make a mistake.",
            "description": "",
            "category": "indonesian"
        },
        {
            "text": "No matter how stressed or angry we are, we have to solve a problem with rationale.",
            "description": "",
            "category": "indonesian"
        },
        {
            "text": "No matter how successful a person is, he will experience some bad things too.",
            "description": "",
            "category": "indonesian"
        },
        {
            "text": "No pain no gain.",
            "description": "",
            "category": "indonesian"
        },
        {
            "text": "Nothing is difficult if you're used to it.",
            "description": "",
            "category": "indonesian"
        },
        {
            "text": "Nothing is difficult when you get used to it.",
            "description": "",
            "category": "indonesian"
        },
        {
            "text": "Nothing is perfect in this world.",
            "description": "",
            "category": "indonesian"
        },
        {
            "text": "Older but instead of getting wiser, one gets naughtier.",
            "description": "",
            "category": "indonesian"
        },
        {
            "text": "Once the rice is pudding, it's too late to reclaim the rice.",
            "description": "",
            "category": "indonesian"
        },
        {
            "text": "Once you lost the trust of someone, it is almost impossible to gain it back.",
            "description": "",
            "category": "indonesian"
        },
        {
            "text": "Beautiful day, a gift for the traveller.",
            "description": "",
            "category": "indonesian"
        },
        {
            "text": "Before you let your voice be heard, first lick your lips.",
            "description": "",
            "category": "indonesian"
        },
        {
            "text": "Better something than nothing.",
            "description": "",
            "category": "indonesian"
        },
        {
            "text": "Beware, the enemy lies under your blanket.",
            "description": "",
            "category": "indonesian"
        },
        {
            "text": "Blaming the wrong reason. Looking for a scapegoat.",
            "description": "",
            "category": "indonesian"
        },
        {
            "text": "Blaming the wrong reason/cause or creating a scapegoat.",
            "description": "",
            "category": "indonesian"
        },
        {
            "text": "Calm water does not mean there are no crocodiles.",
            "description": "",
            "category": "indonesian"
        },
        {
            "text": "Changing priorities.",
            "description": "",
            "category": "indonesian"
        },
        {
            "text": "Collaboration, sharing of burden irrespective of the weight.",
            "description": "",
            "category": "indonesian"
        },
        {
            "text": "Death is the bride of life.",
            "description": "",
            "category": "indonesian"
        },
        {
            "text": "A person who is extremely cautious in doing something.",
            "description": "",
            "category": "indonesian"
        },
        {
            "text": "A person who loves about their mother is doing the best deed.",
            "description": "",
            "category": "indonesian"
        },
        {
            "text": "A person who talks a lot usually is empty inside.",
            "description": "",
            "category": "indonesian"
        },
        {
            "text": "A person who wish for something impossible.",
            "description": "",
            "category": "indonesian"
        },
        {
            "text": "A smart man is usually humble.",
            "description": "",
            "category": "indonesian"
        },
        {
            "text": "All the bad things seems to happen at the same time.",
            "description": "",
            "category": "indonesian"
        },
        {
            "text": "An egoistic person can't realize his own mistakes, but can always find mistakes of others.",
            "description": "",
            "category": "indonesian"
        },
        {
            "text": "Asking question is the only way to learn.",
            "description": "",
            "category": "indonesian"
        },
        {
            "text": "Be careful of what you say as it can hurt more than a knife.",
            "description": "",
            "category": "indonesian"
        },
        {
            "text": "Be dilligent in learning.",
            "description": "",
            "category": "indonesian"
        },
        {
            "text": "Most people don’t announce their faults with a gong.",
            "description": "",
            "category": "indonesian"
        },
        {
            "text": "Nothing is difficult if you’re used to it.",
            "description": "",
            "category": "indonesian"
        },
        {
            "text": "Don’t stay on the dew until the sun reaches its highest.",
            "description": "",
            "category": "indonesian"
        },
        {
            "text": "The name of Love’s fiance is Divorce.",
            "description": "",
            "category": "indonesian"
        },
        {
            "text": "Goodnesss houts. Evil whispers.",
            "description": "",
            "category": "indonesian"
        },
        {
            "text": "The name of Love’s fiancee is Divorce.",
            "description": "",
            "category": "indonesian"
        },
        {
            "text": "Once the rice is pudding, it’s too late to reclaim the rice.",
            "description": "",
            "category": "indonesian"
        },
        {
            "text": "Death is the bride of life. ",
            "description": "",
            "category": "indonesian"
        },
        {
            "text": "When you begin to understand the situation, you know you must have been ill-informed. ",
            "description": "",
            "category": "indonesian"
        },
        {
            "text": "Different men have different opinions; some like apples, some onions.",
            "description": "",
            "category": "indonesian"
        },
        {
            "text": "Different men have different opinions — some prefer apples, some onions.",
            "description": "",
            "category": "indonesian"
        },
        {
            "text": "A person slips, and a ladder falls on him.",
            "description": "",
            "category": "indonesian"
        },
        {
            "text": "Moth will eat the finest linen.",
            "description": "",
            "category": "indonesian"
        },
        {
            "text": "An empty drum gives loud sound.",
            "description": "",
            "category": "indonesian"
        },
        {
            "text": "Be sick then have fun.",
            "description": "",
            "category": "indonesian"
        },
        {
            "text": "Better one bird in the hand than 10 birds on the tree.",
            "description": "",
            "category": "indonesian"
        },
        {
            "text": "Cannot dance but blame the floor as uneven.",
            "description": "",
            "category": "indonesian"
        },
        {
            "text": "Different fields have different insect, different ponds have different fish.",
            "description": "",
            "category": "indonesian"
        },
        {
            "text": "Different men have different opinions; some prefer apples, some onions.",
            "description": "",
            "category": "indonesian"
        },
        {
            "text": "Expecting something bigger and we let go what we already have.",
            "description": "",
            "category": "indonesian"
        },
        {
            "text": "Freedom or death.",
            "description": "",
            "category": "indonesian"
        },
        {
            "text": "Head can be heated but heart must stay cool.",
            "description": "",
            "category": "indonesian"
        },
        {
            "text": "If you give your liver, they ask for your heart.",
            "description": "",
            "category": "indonesian"
        },
        {
            "text": "It can be because of regular training.",
            "description": "",
            "category": "indonesian"
        },
        {
            "text": "Never think that still water doesn’t have crocodiles.",
            "description": "",
            "category": "indonesian"
        },
        {
            "text": "No matter how good a squirrel can jump, it will fall eventually.",
            "description": "",
            "category": "indonesian"
        },
        {
            "text": "Once a person cheats in an exam, forever people will distrust him.",
            "description": "",
            "category": "indonesian"
        },
        {
            "text": "One stroke at the paddle, two and three islands have passed.",
            "description": "",
            "category": "indonesian"
        },
        {
            "text": "People seek out big shots as flies seek out the elephant’s tail.",
            "description": "",
            "category": "indonesian"
        },
        {
            "text": "Playing with water, wet. Playing with fire, burned.",
            "description": "",
            "category": "indonesian"
        },
        {
            "text": "Still water runs deep.",
            "description": "",
            "category": "indonesian"
        }
    ]
}