{
    "swiss": [
        {
            "text": "Little strokes fell great oaks.",
            "description": "",
            "category": "swiss"
        },
        {
            "text": "When one shuts one eye, one does not hear everything.",
            "description": "",
            "category": "swiss"
        },
        {
            "text": "Where it is customary the cow is brought to bed.",
            "description": "",
            "category": "swiss"
        },
        {
            "text": "Who cares about every little feather should not make the bed.",
            "description": "",
            "category": "swiss"
        },
        {
            "text": "Words are dwarfs, deeds are giants.",
            "description": "",
            "category": "swiss"
        },
        {
            "text": "A good spectator also creates.",
            "description": "",
            "category": "swiss"
        },
        {
            "text": "A greedy person and a pauper are practically one and the same.",
            "description": "",
            "category": "swiss"
        },
        {
            "text": "As the stone leaves your hand it belongs to the devil.",
            "description": "",
            "category": "swiss"
        },
        {
            "text": "Ask ten brewers and you will get eleven opinions.",
            "description": "",
            "category": "swiss"
        },
        {
            "text": "At the bottom of the sack you will find the bill.",
            "description": "",
            "category": "swiss"
        },
        {
            "text": "Avoid those who don't like bread and children.",
            "description": "",
            "category": "swiss"
        },
        {
            "text": "Better to sell it with regret than to keep it.",
            "description": "",
            "category": "swiss"
        },
        {
            "text": "Better to sell with regret than to keep with regret.",
            "description": "",
            "category": "swiss"
        },
        {
            "text": "God lets things go -- but only to a point.",
            "description": "",
            "category": "swiss"
        },
        {
            "text": "Great consolation may grow out of the smallest saying.",
            "description": "",
            "category": "swiss"
        },
        {
            "text": "He that sleeps sound feels not the toothache.",
            "description": "",
            "category": "swiss"
        },
        {
            "text": "He who mocks the cripple should be straight himself.",
            "description": "",
            "category": "swiss"
        },
        {
            "text": "If you close one eye, you will not hear everything.",
            "description": "",
            "category": "swiss"
        },
        {
            "text": "In a house of gold the clocks are of lead.",
            "description": "",
            "category": "swiss"
        },
        {
            "text": "It is always the fat ones who lead the dance.",
            "description": "",
            "category": "swiss"
        },
        {
            "text": "It is easier to beat two devils into a child, than one devil out.",
            "description": "",
            "category": "swiss"
        },
        {
            "text": "It is easier to criticize than to do better.",
            "description": "",
            "category": "swiss"
        },
        {
            "text": "Marriage is a covered dish.",
            "description": "",
            "category": "swiss"
        },
        {
            "text": "One simple maxim is often worth more than two good friends.",
            "description": "",
            "category": "swiss"
        },
        {
            "text": "Sometimes you have to be silent in order to be heard It's easier to criticize than to do better.",
            "description": "",
            "category": "swiss"
        },
        {
            "text": "The devil hides himself in details.\"",
            "description": "",
            "category": "swiss"
        },
        {
            "text": "The night rinses what the day has soaped.",
            "description": "",
            "category": "swiss"
        },
        {
            "text": "The poor lack much, but the greedy lack more.",
            "description": "",
            "category": "swiss"
        },
        {
            "text": "The tongue is the worst piece of meat in the world.",
            "description": "",
            "category": "swiss"
        },
        {
            "text": "To be a fool at the right time is also an art.",
            "description": "",
            "category": "swiss"
        },
        {
            "text": "What good is a golden gallows if they are going to hang you.",
            "description": "",
            "category": "swiss"
        },
        {
            "text": "When a merchant talks about sheep he means the hide.",
            "description": "",
            "category": "swiss"
        },
        {
            "text": "When a neighbor gets divorced everyone thinks of his own wife.",
            "description": "",
            "category": "swiss"
        },
        {
            "text": "When in doubt who will win, be neutral.",
            "description": "",
            "category": "swiss"
        },
        {
            "text": "Sometimes you must be silent in order to be heard.",
            "description": "",
            "category": "swiss"
        },
        {
            "text": "Speech is silver; silence is golden.",
            "description": "",
            "category": "swiss"
        },
        {
            "text": "Words are but dwarfs, deeds are giants.",
            "description": "",
            "category": "swiss"
        },
        {
            "text": "The poor lack much, but the greedy more.",
            "description": "",
            "category": "swiss"
        },
        {
            "text": "What the farmer doesn’t know, he will not eat.",
            "description": "",
            "category": "swiss"
        },
        {
            "text": "Sometimes you have to be silent in order to be heard.",
            "description": "",
            "category": "swiss"
        },
        {
            "text": "The devil hides himself in details.",
            "description": "",
            "category": "swiss"
        },
        {
            "text": "Avoid those who don’t like bread and children.",
            "description": "",
            "category": "swiss"
        },
        {
            "text": "Luck is on your path, one takes it, the other passes by it.",
            "description": "",
            "category": "swiss"
        },
        {
            "text": "Mountains and valleys stand firm but people meet.",
            "description": "",
            "category": "swiss"
        },
        {
            "text": "Every man is the maker of his own fortune.",
            "description": "",
            "category": "swiss"
        },
        {
            "text": "A swallow does not make a summer.",
            "description": "",
            "category": "swiss"
        },
        {
            "text": "It’s easier to criticize than to do better.",
            "description": "",
            "category": "swiss"
        },
        {
            "text": "Big fish eat little fish.",
            "description": "",
            "category": "swiss"
        },
        {
            "text": "The French work to live, but the Swiss live to work.",
            "description": "",
            "category": "swiss"
        },
        {
            "text": "The apple does not fall far from the tree.",
            "description": "",
            "category": "swiss"
        },
        {
            "text": "Think first, start later.",
            "description": "",
            "category": "swiss"
        },
        {
            "text": "You learn how to cook on old pans.",
            "description": "",
            "category": "swiss"
        },
        {
            "text": "He who starts well is in the middle of the work.",
            "description": "",
            "category": "swiss"
        },
        {
            "text": "A clean house is a clean mind.",
            "description": "",
            "category": "swiss"
        },
        {
            "text": "If everyone looks after themselves, everyone is looked after.",
            "description": "",
            "category": "swiss"
        },
        {
            "text": "Each problem has two sides, the wrong side and ours.",
            "description": "",
            "category": "swiss"
        },
        {
            "text": "You should not add oil to the fire.",
            "description": "",
            "category": "swiss"
        },
        {
            "text": "God lets things go, but only to a point.",
            "description": "",
            "category": "swiss"
        },
        {
            "text": "Measure thrice, cut once.",
            "description": "",
            "category": "swiss"
        },
        {
            "text": "Time’s most valuable when you don’t have it.",
            "description": "",
            "category": "swiss"
        },
        {
            "text": "You learn through mistakes – no one was born a master.",
            "description": "",
            "category": "swiss"
        },
        {
            "text": "He who does not work is without food.",
            "description": "",
            "category": "swiss"
        },
        {
            "text": "It is good fishing in streamy water.",
            "description": "",
            "category": "swiss"
        },
        {
            "text": "No money, no Swiss.",
            "description": "",
            "category": "swiss"
        }
    ]
}